{"name": "İzmir_ilinde_siyaset", "id": 1128679, "predecessors": [{"name": "Ege_Denizi", "id": 192531}, {"name": "Türkiye'de_siyaset", "id": 1194278}], "successors": [{"name": "İzmir_valileri", "id": 211331}, {"name": "İzmir_belediye_başkanları", "id": 448171}, {"name": "TBMM_23._dönem_İzmir_milletvekilleri", "id": 378012}, {"name": "TBMM_22._dönem_İzmir_milletvekilleri", "id": 378019}, {"name": "TBMM_18._dönem_İzmir_milletvekilleri", "id": 378049}, {"name": "TBMM_20._dönem_İzmir_milletvekilleri", "id": 378188}, {"name": "TBMM_7._dönem_İzmir_milletvekilleri", "id": 381213}, {"name": "TBMM_10._dönem_İzmir_milletvekilleri", "id": 381263}, {"name": "TBMM_11._dönem_İzmir_milletvekilleri", "id": 381264}, {"name": "TBMM_15._dönem_İzmir_milletvekilleri", "id": 381453}, {"name": "TBMM_13._dönem_İzmir_milletvekilleri", "id": 382744}, {"name": "TBMM_9._dönem_İzmir_milletvekilleri", "id": 391936}, {"name": "TBMM_24._dönem_İzmir_milletvekilleri", "id": 1304801}, {"name": "TBMM_25._dönem_İzmir_milletvekilleri", "id": 1935605}, {"name": "TBMM_26._dönem_İzmir_milletvekilleri", "id": 2041153}, {"name": "TBMM_27._dönem_İzmir_milletvekilleri", "id": 2338122}, {"name": "TBMM_28._dönem_İzmir_milletvekilleri", "id": 3548663}, {"name": "İzmir_Büyükşehir_Belediyesi_meclis_üyeleri", "id": 2928426}]}