{"name": "İslam_ve_siyaset", "id": 187131, "predecessors": [{"name": "Din_ve_siyaset", "id": 1584780}], "successors": [{"name": "İslam_hukuku", "id": 54339}, {"name": "İslamcılık", "id": 709451}, {"name": "Müslüman_Kardeşler", "id": 721958}, {"name": "Müslümanlaştırma", "id": 1516068}, {"name": "İslamcı_partiler", "id": 1528894}, {"name": "Pan-İslamizm", "id": 1608624}, {"name": "İslami_demokrasi", "id": 2081940}, {"name": "İki_kutsal_caminin_hizmetkârları", "id": 2174430}, {"name": "Direniş_Ekseni", "id": 2848823}]}