{"name": "Sanayi", "id": 21457, "predecessors": [{"name": "İşletme", "id": 21253}, {"name": "Teknoloji", "id": 6300}], "successors": [{"name": "Hayvancılık", "id": 42809}, {"name": "Endüstri_mühendisliği", "id": 212864}, {"name": "Sanayi_Devrimi", "id": 416817}, {"name": "Çevre_kirliliği", "id": 769780}, {"name": "Yapım,_üretim_ve_imalat", "id": 907045}, {"name": "Endüstriyel_işlemler", "id": 1571841}, {"name": "Mobilya", "id": 981396}, {"name": "Türkiye_merkezli_enerji_şirketleri", "id": 862983}, {"name": "Amerika_Birleşik_Devletleri_merkezli_imalat_şirketleri", "id": 895335}, {"name": "Almanya_merkezli_imalat_şirketleri", "id": 1080697}, {"name": "Japonya_merkezli_imalat_şirketleri", "id": 1472534}, {"name": "Türkiye_merkezli_imalat_şirketleri", "id": 1930124}, {"name": "Amerika_Birleşik_Devletleri_merkezli_kimya_şirketleri", "id": 932314}, {"name": "Amerika_Birleşik_Devletleri_merkezli_finans_şirketleri", "id": 1953270}, {"name": "Birleşik_Krallık_merkezli_savunma_şirketleri", "id": 2232411}, {"name": "Üç_boyutlu_grafik_tasarım_yazılımları", "id": 355768}, {"name": "Kurgusal_tamirciler", "id": 1387266}, {"name": "Fransa_merkezli_otomotiv_şirketleri", "id": 277023}, {"name": "Türkiye_merkezli_inşaat_şirketleri", "id": 1411394}, {"name": "Türkiye'deki_hidroelektrik_santralleri", "id": 1406283}, {"name": "Hyundai_otomobilleri", "id": 1105956}, {"name": "Kia_otomobilleri", "id": 1105971}, {"name": "Japonya_merkezli_motor_üreticileri", "id": 2465344}]}