{"name": "Rus_İmparatorluğu", "id": 2201438, "predecessors": [{"name": "Emperyalizm", "id": 36580}, {"name": "Eski_Slav_ülkeler", "id": 2045014}, {"name": "Süper_güçler", "id": 1429394}, {"name": "Rusya_tarihi", "id": 55654}], "successors": [{"name": "Rus_Devrimi", "id": 489193}, {"name": "Rus_Devrimi_(1905)", "id": 1760888}, {"name": "Rus_İmparatorluğu_kişileri", "id": 2201418}, {"name": "Rus_İmparatorluğu_sonrası_devletler", "id": 2268269}, {"name": "Rus_İmparatorluğu_askerî_personeli", "id": 2201421}, {"name": "Rus_İmparatorluğu_dışişleri_bakanları", "id": 2276231}]}