{"name": "Çin_imparatorları", "id": 397961, "predecessors": [{"name": "Çin_hükümdarları", "id": 1606734}, {"name": "İmparatorlar", "id": 79650}, {"name": "Çin_tarihi", "id": 100089}], "successors": [{"name": "Yuan_Hanedanı_hanları", "id": 795927}, {"name": "Han_Hanedanı_imparatorları", "id": 1303330}, {"name": "Üç_Hükümdar_ve_Beş_İmparator", "id": 1315350}, {"name": "Çing_Hanedanı_imparatorları", "id": 1315354}, {"name": "Ming_Hanedanı_imparatorları", "id": 1315361}, {"name": "Tang_Hanedanı_imparatorları", "id": 1315366}, {"name": "Song_Hanedanı_imparatorları", "id": 2220950}, {"name": "Üç_İmparatorluk_imparatorları", "id": 3444552}, {"name": "Jin_Hanedanı_(265-420)_imparatorları", "id": 3445204}, {"name": "Kuzey_Vey_imparatorları", "id": 3468189}, {"name": "Liao_Hanedanı_imparatorları", "id": 3470545}]}