{"name": "Heavy_metal", "id": 421141, "predecessors": [{"name": "Amerika'da_müzik_tarzları", "id": 902350}, {"name": "Rock_müzik_tarzları", "id": 853298}], "successors": [{"name": "Heavy_metal_albümleri", "id": 93149}, {"name": "Heavy_metal_alttarzları", "id": 966991}, {"name": "Heavy_metal_grupları", "id": 83485}, {"name": "Amerikalı_heavy_metal_şarkıcıları", "id": 470052}, {"name": "Alternatif_metal_müzisyenleri", "id": 1788266}, {"name": "Norveçli_black_metal_müzisyenleri", "id": 1322158}, {"name": "Black_metal_grubu_şablonları", "id": 1325818}, {"name": "Norveçli_black_metal_grupları", "id": 1181781}, {"name": "Norveçli_heavy_metal_grubu_şablonları", "id": 1325816}, {"name": "Amerikalı_heavy_metal_grubu_şablonları", "id": 1325826}, {"name": "Heavy_metal_grupları_diskografileri", "id": 1386236}]}