{"name": "Eurovision_Şarkı_Yarışması", "id": 451697, "predecessors": [{"name": "Yarışma_programları", "id": 199962}, {"name": "Şarkı_yarışmaları", "id": 1007351}, {"name": "Felsefe", "id": 6586}, {"name": "Avrupa'daki_bölgeler", "id": 1767247}, {"name": "Fizik_terimleri", "id": 1808406}], "successors": [{"name": "Eurovision_Şarkı_Yarışması_sunucuları", "id": 451696}, {"name": "Eurovision_Şarkı_Yarışması'nda_ülkeler", "id": 1554602}, {"name": "Yıllara_göre_Eurovision_Şarkı_Yarışması_şablonları", "id": 1573264}]}