{"name": "Video_oyunu_serileri", "id": 456273, "predecessors": [{"name": "Medya_imtiyazları", "id": 978137}, {"name": "Video_oyunları", "id": 450124}, {"name": "Oyunlar", "id": 10599}], "successors": [{"name": "Pokémon", "id": 22481}, {"name": "Digimon", "id": 102450}, {"name": "Fallout_serisi", "id": 369289}, {"name": "Kirpi_Sonic", "id": 779043}, {"name": "Video_oyun_devamları", "id": 911447}, {"name": "Age_of_Empires", "id": 1104520}, {"name": "Civilization", "id": 1104825}, {"name": "God_of_War", "id": 1133729}, {"name": "Spider-Man_oyunları", "id": 1150146}, {"name": "Yıldız_Savaşları_video_oyunları", "id": 1201404}, {"name": "LittleBigPlanet", "id": 1286630}, {"name": "Silent_Hill", "id": 1737290}, {"name": "Dead_Space", "id": 1738436}, {"name": "Postal_(video_oyunu_serisi)", "id": 2006053}, {"name": "Final_Fantasy", "id": 2291674}, {"name": "Hugo_(seri)", "id": 2311576}, {"name": "Fate/stay_night", "id": 2373923}, {"name": "Kingdom_Hearts", "id": 2470397}, {"name": "Forza", "id": 2515313}]}