{"name": "Berlin_tarihi", "id": 662899, "predecessors": [{"name": "Devlet_kurumları", "id": 1016288}], "successors": [{"name": "Bauhaus", "id": 939450}, {"name": "Berlin_Muharebesi", "id": 1109926}, {"name": "1936_Yaz_Olimpiyatları_atletleri", "id": 394296}, {"name": "1936_Yaz_Olimpiyatları_eskrimcileri", "id": 1436011}, {"name": "1936_Yaz_Olimpiyatları_güreşçileri", "id": 1539606}, {"name": "1936_Yaz_Olimpiyatları_basketbolcuları", "id": 1613636}, {"name": "1936_Yaz_Olimpiyatları_futbolcuları", "id": 1630959}, {"name": "1936_Yaz_Olimpiyatları_yüzücüleri", "id": 1630960}]}