{"name": "Kavramlar", "id": 6788, "predecessors": [{"name": "Anlambilim", "id": 262103}, {"name": "Biliş", "id": 92791}, {"name": "Düşünce", "id": 92725}, {"name": "Vikipedi", "id": 7220}], "successors": [{"name": "Bilgi", "id": 12510}, {"name": "Terimler", "id": 81201}, {"name": "Teoriler", "id": 93032}, {"name": "Yazı_sistemleri", "id": 72682}, {"name": "Sistem_teorisi", "id": 189068}, {"name": "Sistem_mühendisliği", "id": 388018}, {"name": "Koordinat_sistemleri", "id": 517302}, {"name": "Ağlar", "id": 686745}, {"name": "Kütüphane_sistemleri", "id": 945560}, {"name": "Bilimsel_modelleme", "id": 379806}, {"name": "Düşünce_deneyleri", "id": 182533}, {"name": "Diyagramlar", "id": 1166850}, {"name": "Felsefi_kavramlar", "id": 12229}, {"name": "Sosyoloji_kavramları", "id": 188161}, {"name": "Meteoroloji_kavram_ve_fenomenleri", "id": 902742}, {"name": "Edebiyat_kavramları", "id": 1415837}, {"name": "Dinî_kavramlar", "id": 1580218}, {"name": "Siyasi_kavramlar", "id": 1904088}, {"name": "Psikoloji_kavramları", "id": 2460631}, {"name": "İklim_değişikliği", "id": 402532}, {"name": "Suç", "id": 23210}, {"name": "Ayrımcılık", "id": 25714}, {"name": "Çocuk_istismarı_konulu_filmler", "id": 2283380}, {"name": "Güvenlik", "id": 36571}, {"name": "Hijyen", "id": 86836}, {"name": "Gıda_güvenliği", "id": 1664258}, {"name": "Bilimsel_yasalar", "id": 949226}, {"name": "Hukuk_yasaları", "id": 949293}, {"name": "Futbol_kuralları", "id": 12953}, {"name": "Türkiye'de_spor_yönetim_kuruluşları", "id": 857581}]}