{"name": "Batı_sanatı", "id": 780474, "predecessors": [{"name": "Sanat_tarihi", "id": 10390}, {"name": "Sosyoloji", "id": 1145186}], "successors": [{"name": "Modern_sanat", "id": 12419}, {"name": "Postmodernizm", "id": 16830}, {"name": "Dadaizm", "id": 21094}, {"name": "Romantizm", "id": 52444}, {"name": "Aydınlanma_Çağı", "id": 69207}, {"name": "Akademik_sanat", "id": 840241}, {"name": "Orta_Çağ_sanatı", "id": 902395}, {"name": "Rönesans'ta_kişiler", "id": 1930035}, {"name": "Fransız_edebiyatı", "id": 76898}, {"name": "Fransa_filmleri", "id": 337706}, {"name": "Fransız_senaristler", "id": 420635}, {"name": "César_Ödülü_sahipleri", "id": 529768}, {"name": "Fransız_film_yönetmenleri", "id": 810387}, {"name": "Fransız_film_yapımcıları", "id": 813393}, {"name": "Fransa'da_çekilmiş_filmler", "id": 1388351}, {"name": "Uyumsuz_tiyatro", "id": 172583}, {"name": "Gerçeküstücü_sanatçılar", "id": 344378}, {"name": "Fransız_erkek_sinema_oyuncuları", "id": 1951259}, {"name": "Fransız_kadın_sinema_oyuncuları", "id": 1951265}, {"name": "Barok_müzik", "id": 93976}, {"name": "Post-empresyonist_ressamlar", "id": 75690}, {"name": "Vincent_van_Gogh_tabloları", "id": 820981}, {"name": "Art_Nouveau_mimarisi", "id": 3231733}, {"name": "Danimarkalı_film_yönetmenleri", "id": 1042941}, {"name": "Bodil_Ödülü_sahipleri", "id": 2170661}, {"name": "Romanesk_mimari", "id": 917950}, {"name": "Gerçeküstücü_filmler", "id": 568295}, {"name": "Gotik_mimari", "id": 856083}]}