{"name": "Türkiye'deki_şehirler", "id": 81605, "predecessors": [{"name": "Siyasi_coğrafya", "id": 36581}], "successors": [{"name": "Türkiye'deki_antik_kentler", "id": 1303911}, {"name": "Hatay_ili_tarihi", "id": 384239}, {"name": "Erzurum_ili_tarihi", "id": 384249}, {"name": "İzmir_tarihi", "id": 384254}, {"name": "Şanlıurfa_ili_tarihi", "id": 390415}, {"name": "Kars_ili_tarihi", "id": 390422}, {"name": "Çanakkale_ili_tarihi", "id": 390424}, {"name": "Aydın_ili_tarihi", "id": 390434}, {"name": "Bursa_ili_tarihi", "id": 390436}, {"name": "Balıkesir_ili_tarihi", "id": 415602}, {"name": "Erzincan_ili_tarihi", "id": 437592}, {"name": "Van_ili_tarihi", "id": 550397}, {"name": "Kütahya_ili_tarihi", "id": 685625}, {"name": "Kastamonu_ili_tarihi", "id": 685632}, {"name": "Trabzon_ili_tarihi", "id": 686544}, {"name": "Ardahan_ili_tarihi", "id": 687184}, {"name": "Artvin_ili_tarihi", "id": 811272}, {"name": "Edirne_ili_tarihi", "id": 811281}, {"name": "Konya_ili_tarihi", "id": 811287}, {"name": "Mersin_ili_tarihi", "id": 811291}, {"name": "Tokat_ili_tarihi", "id": 811297}, {"name": "Sinop_ili_tarihi", "id": 1131819}, {"name": "Samsun_ili_tarihi", "id": 1305282}, {"name": "Hakkâri_ili_tarihi", "id": 1305301}, {"name": "Bingöl_ili_tarihi", "id": 1306661}, {"name": "Ankara'daki_cumhuriyet_dönemi_yapıları", "id": 157856}, {"name": "Ankara_ilindeki_arkeolojik_sitler", "id": 372660}, {"name": "Ankara'daki_Osmanlı_yapıları", "id": 2362668}, {"name": "Lidya", "id": 231885}, {"name": "Manisa_ilindeki_arkeolojik_sitler", "id": 349308}, {"name": "İstanbul_gazeteleri", "id": 93561}, {"name": "Karaman_merkez_belde_ve_köyleri", "id": 1626356}, {"name": "İstanbul_ilindeki_festivaller", "id": 383558}, {"name": "İstanbul'da_düzenlenen_spor_etkinlikleri", "id": 1143192}, {"name": "Konstantinopolis_kuşatmaları", "id": 1041988}, {"name": "Ankara'daki_tarih_müzeleri", "id": 2451621}, {"name": "Ankara'da_düzenlenen_spor_etkinlikleri", "id": 2570105}, {"name": "İzmir_ilindeki_görülecek_yerler", "id": 1016016}, {"name": "Ankara'nın_semtleri", "id": 356947}, {"name": "Çankaya'daki_cadde_ve_sokaklar", "id": 2516885}, {"name": "Muratpaşa'daki_yapılar", "id": 4229889}]}