{"name": "Amerika_Birleşik_Devletleri'ndeki_etnik_gruplar", "id": 88519, "predecessors": [{"name": "Levha_tektoniği", "id": 376631}], "successors": [{"name": "Afrikalı_Amerikanlar", "id": 448306}, {"name": "Meksika_asıllı_Amerikalılar", "id": 868574}, {"name": "Aşkenaz_Yahudileri", "id": 947415}, {"name": "Türk_asıllı_Amerikalılar", "id": 953788}, {"name": "Japon_asıllı_Amerikalılar", "id": 1048014}, {"name": "Kore_asıllı_Amerikalılar", "id": 1085843}, {"name": "Ahıska_Türkleri", "id": 1403749}, {"name": "Norveçli_taslakları", "id": 981851}, {"name": "İngiliz_taslakları", "id": 182523}, {"name": "İngiltere_kral_ve_kraliçeleri", "id": 485308}, {"name": "İngiliz_aktivistler", "id": 1170379}, {"name": "Kurgusal_İngilizler", "id": 1201642}, {"name": "İngiliz_kadınlar", "id": 1305698}, {"name": "İngiliz_vejetaryenler", "id": 1321801}, {"name": "İngiliz_hümanistler", "id": 2068797}, {"name": "100_yaş_üstü_İngilizler", "id": 2119892}, {"name": "İngiliz_soylular", "id": 2150699}, {"name": "Royal_Society_üyesi_İngilizler", "id": 4103910}, {"name": "İsveçli_taslakları", "id": 723379}, {"name": "İsveçli_soylular", "id": 1445046}, {"name": "Amerika_Birleşik_Devletleri_Kızılderilileri", "id": 1560118}, {"name": "Kıbrıs_Türkü_kişileri_taslakları", "id": 1211138}, {"name": "Kıbrıs_Rumu_kişileri_taslakları", "id": 1789382}, {"name": "Charles_Darwin", "id": 732368}, {"name": "Fin_taslakları", "id": 1178258}, {"name": "Kıbrıs_Rumu_siyasetçiler", "id": 1406666}, {"name": "Kıbrıs_Türkü_siyasetçiler", "id": 503739}, {"name": "Kıbrıs_Türkü_gazeteciler", "id": 821186}, {"name": "Kıbrıs_Türkü_asıllı_Britanyalılar", "id": 1490475}, {"name": "Finlandiya_İsveçlileri", "id": 1177998}, {"name": "Carl_Linnaeus_tarafından_adlandırılmış_taksonlar", "id": 2400065}, {"name": "Norveçli_gurbetçi_futbolcular", "id": 1665518}, {"name": "Almanya'daki_Norveçli_gurbetçiler", "id": 1713837}, {"name": "Danimarka'daki_Norveçli_gurbetçiler", "id": 1743508}, {"name": "İsveçli_gurbetçi_futbolcular", "id": 1294294}, {"name": "Hollanda'daki_İsveçli_gurbetçiler", "id": 1696323}, {"name": "Türkiye'deki_İsveçli_gurbetçiler", "id": 1696346}, {"name": "Danimarka'daki_İsveçli_gurbetçiler", "id": 1696348}, {"name": "İtalya'daki_İsveçli_gurbetçiler", "id": 1698636}, {"name": "Almanya'daki_İsveçli_gurbetçiler", "id": 1698660}, {"name": "Amerika_Birleşik_Devletleri'ndeki_İngiliz_göçmenler", "id": 1814034}, {"name": "Avustralya'daki_İngiliz_göçmenler", "id": 2612998}, {"name": "Fin_güzellik_yarışması_birincileri", "id": 2227406}, {"name": "Fin_kadın_siyasetçiler", "id": 2037146}, {"name": "Fin_kadın_modeller", "id": 2212782}, {"name": "Yunan_asıllı_Amerikalılar", "id": 377128}, {"name": "Yahudi_asıllı_Amerikalılar", "id": 379875}, {"name": "Macar_asıllı_Amerikalılar", "id": 460514}, {"name": "İtalyan_asıllı_Amerikalılar", "id": 488721}, {"name": "Polonya_asıllı_Amerikalılar", "id": 512213}, {"name": "Ermeni_asıllı_Amerikalılar", "id": 595170}, {"name": "Rus_asıllı_Amerikalılar", "id": 707895}, {"name": "Alman_asıllı_Amerikalılar", "id": 760056}, {"name": "Portekiz_asıllı_Amerikalılar", "id": 781474}, {"name": "İrlanda_asıllı_Amerikalılar", "id": 796901}, {"name": "Sırp_asıllı_Amerikalılar", "id": 806527}, {"name": "İsveç_asıllı_Amerikalılar", "id": 815184}, {"name": "Amerika_Birleşik_Devletleri_vatandaşlığına_kabul_edilenler", "id": 825838}, {"name": "Küba_asıllı_Amerikalılar", "id": 834702}, {"name": "Avusturya_asıllı_Amerikalılar", "id": 838886}, {"name": "Arnavut_asıllı_Amerikalılar", "id": 838890}, {"name": "Hollanda_asıllı_Amerikalılar", "id": 857402}, {"name": "Çin_asıllı_Amerikalılar", "id": 857447}, {"name": "Dominik_Cumhuriyeti_asıllı_Amerikalılar", "id": 857531}, {"name": "Fransız_asıllı_Amerikalılar", "id": 857551}, {"name": "Ukrayna_asıllı_Amerikalılar", "id": 987261}, {"name": "Avustralya_asıllı_Amerikalılar", "id": 1051194}, {"name": "İspanyol_asıllı_Amerikalılar", "id": 1054807}, {"name": "İran_asıllı_Amerikalılar", "id": 1073124}, {"name": "Filipin_asıllı_Amerikalılar", "id": 1188317}, {"name": "Fin_asıllı_Amerikalılar", "id": 1286997}, {"name": "Hint_asıllı_Amerikalılar", "id": 1291975}, {"name": "Kanada_asıllı_Amerikalılar", "id": 1292160}, {"name": "Danimarka_asıllı_Amerikalılar", "id": 1292291}, {"name": "Litvan_asıllı_Amerikalılar", "id": 1294172}, {"name": "Norveç_asıllı_Amerikalılar", "id": 1304865}, {"name": "Rumen_asıllı_Amerikalılar", "id": 1307611}, {"name": "Slovak_asıllı_Amerikalılar", "id": 1333508}, {"name": "Suriye_asıllı_Amerikalılar", "id": 1350578}, {"name": "Britanya_asıllı_Amerikalılar", "id": 1403706}, {"name": "Çek_asıllı_Amerikalılar", "id": 1415185}, {"name": "Kızılderili_asıllı_Amerikalılar", "id": 1481959}, {"name": "Lübnan_asıllı_Amerikalılar", "id": 1483014}, {"name": "Jamaika_asıllı_Amerikalılar", "id": 1491607}, {"name": "İsrail_asıllı_Amerikalılar", "id": 1493680}, {"name": "İsviçre_asıllı_Amerikalılar", "id": 1513412}, {"name": "Porto_Riko_asıllı_Amerikalılar", "id": 1691375}, {"name": "Nijerya_asıllı_Amerikalılar", "id": 1808679}, {"name": "Türk_asıllı_İsveçliler", "id": 1129148}, {"name": "Alman_asıllı_İsveçliler", "id": 1252665}, {"name": "İsveç'teki_gurbetçi_futbolcular", "id": 1612375}, {"name": "Norveç'teki_gurbetçi_futbolcular", "id": 1446105}, {"name": "Türk_asıllı_İngilizler", "id": 1209059}, {"name": "İspanyol_asıllı_İngilizler", "id": 1290554}, {"name": "Alman_asıllı_İngilizler", "id": 1292184}, {"name": "Galler_asıllı_İngilizler", "id": 1292185}, {"name": "Yahudi_asıllı_İngilizler", "id": 1292188}, {"name": "Nijerya_asıllı_İngilizler", "id": 1292966}, {"name": "Hint_asıllı_İngilizler", "id": 1292970}, {"name": "İrlanda_asıllı_İngilizler", "id": 1292986}, {"name": "Fransız_asıllı_İngilizler", "id": 1408340}, {"name": "Jamaika_asıllı_İngilizler", "id": 1454434}, {"name": "İtalyan_asıllı_İngilizler", "id": 1455153}, {"name": "İskoç_asıllı_İngilizler", "id": 1584035}, {"name": "Gana_asıllı_İngilizler", "id": 1768311}, {"name": "Amerika_Birleşik_Devletleri_asıllı_İngilizler", "id": 2318513}, {"name": "İngiltere'deki_Türk_gurbetçiler", "id": 1569153}, {"name": "İngiltere'deki_Arjantinli_gurbetçiler", "id": 1692602}, {"name": "İngiltere'deki_Belçikalı_gurbetçiler", "id": 1694237}, {"name": "İngiltere'deki_Polonyalı_gurbetçiler", "id": 1694298}, {"name": "İngiltere'deki_Senegalli_gurbetçiler", "id": 1694414}, {"name": "İngiltere'deki_Kolombiyalı_gurbetçiler", "id": 1694434}, {"name": "İngiltere'deki_Fransız_gurbetçiler", "id": 1694442}, {"name": "İngiltere'deki_gurbetçi_teknik_direktörler", "id": 1694498}, {"name": "İngiltere'deki_Nijeryalı_gurbetçiler", "id": 1694666}, {"name": "İngiltere'deki_Hollandalı_gurbetçiler", "id": 1695007}, {"name": "İngiltere'deki_Brezilyalı_gurbetçiler", "id": 1695565}, {"name": "İngiltere'deki_Amerikalı_gurbetçiler", "id": 1696198}, {"name": "İngiltere'deki_İspanyol_gurbetçiler", "id": 1696217}, {"name": "İngiltere'deki_İsveçli_gurbetçiler", "id": 1696326}, {"name": "İngiltere'deki_Portekizli_gurbetçiler", "id": 1696344}, {"name": "İngiltere'deki_İrlandalı_gurbetçiler", "id": 1698442}, {"name": "İngiltere'deki_Alman_gurbetçiler", "id": 1698922}, {"name": "İngiltere'deki_Uruguaylı_gurbetçiler", "id": 1700520}, {"name": "İngiltere'deki_Danimarkalı_gurbetçiler", "id": 1700543}, {"name": "İngiltere'deki_Sırp_gurbetçiler", "id": 1700546}, {"name": "İngiltere'deki_İtalyan_gurbetçiler", "id": 1700550}, {"name": "İngiltere'deki_Norveçli_gurbetçiler", "id": 1700631}, {"name": "İngiltere'deki_Fildişi_Sahilli_gurbetçiler", "id": 1700693}, {"name": "İngiltere'deki_Avustralyalı_gurbetçiler", "id": 1701179}, {"name": "Rusya_Yahudisi_asıllı_İngilizler", "id": 1795471}, {"name": "Olof_Palme_Ödülü_sahipleri", "id": 2235348}, {"name": "Belarus_Yahudisi_asıllı_Amerikalılar", "id": 1690628}, {"name": "Ermeni_tarihi", "id": 373933}, {"name": "Sovyet_Ermenileri", "id": 2321870}, {"name": "Kardashian_ailesi", "id": 1711614}, {"name": "Türkiye_Ermenileri", "id": 901278}, {"name": "İran_Ermenileri", "id": 1288675}, {"name": "Gürcistan_Ermenileri", "id": 1507295}, {"name": "İsveçli_erkek_şarkıcılar", "id": 1211603}, {"name": "İsveçli_erkek_dizi_oyuncuları", "id": 1939180}, {"name": "İsveçli_erkek_sinema_oyuncuları", "id": 1939181}, {"name": "20._yüzyılda_İsveçli_erkek_oyuncular", "id": 2564584}, {"name": "21._yüzyılda_İsveçli_erkek_oyuncular", "id": 2564585}, {"name": "İsveçli_erkek_tiyatro_oyuncuları", "id": 2564587}, {"name": "İsveçli_erkek_hentbolcular", "id": 2125757}, {"name": "İsveçli_erkek_futbolcular", "id": 4207247}, {"name": "Norveçli_erkek_şarkıcılar", "id": 1322178}, {"name": "Norveçli_erkek_hentbolcular", "id": 2125745}, {"name": "Norveçli_erkek_futbolcular", "id": 4000455}, {"name": "İngiliz_Nobel_Ödülü_sahipleri", "id": 2127204}, {"name": "Olimpiyat_madalyalı_İngiliz_sporcular", "id": 2351434}, {"name": "Safevî_şahları", "id": 1604208}, {"name": "Zara_Larsson_şarkıları", "id": 2190273}, {"name": "Bush_ailesi", "id": 1954300}, {"name": "Tudor_Hanedanı", "id": 489283}, {"name": "Stuart_Hanedanı", "id": 688723}, {"name": "Ziynet_Sali_şarkıları", "id": 1933451}, {"name": "21._yüzyılda_İsveçli_şarkıcılar", "id": 2081289}, {"name": "Cadbury_markaları", "id": 2403352}, {"name": "Stockholm_doğumlular", "id": 1406436}, {"name": "Malmö_doğumlular", "id": 1499182}, {"name": "Kızılderili_kültürü", "id": 88514}, {"name": "İngiliz_erkek_oyuncular", "id": 1925264}, {"name": "İngiliz_erkek_ressamlar", "id": 2993875}, {"name": "İngiliz_erkek_gitaristler", "id": 3515265}, {"name": "21._yüzyılda_İngiliz_erkek_şarkıcılar", "id": 3471326}, {"name": "21._yüzyıl_İsveçli_yazarları", "id": 2385051}]}