{"name": "Katliamlar", "id": 96266, "predecessors": [{"name": "Suçlar", "id": 23209}, {"name": "Toplu_cinayetler", "id": 793170}, {"name": "Şiddet", "id": 25716}, {"name": "Ölüm", "id": 25717}], "successors": [{"name": "Soykırım", "id": 874426}, {"name": "Katliam_taslakları", "id": 1660686}, {"name": "Amerika_Birleşik_Devletleri'ndeki_katliamlar", "id": 684418}, {"name": "Türkiye'deki_katliamlar", "id": 684454}, {"name": "Azerbaycan'daki_katliamlar", "id": 752304}, {"name": "Irak'taki_katliamlar", "id": 791624}]}